{
  "speech_text": "我看了大家说的，有个事让我心里特别不好受。SEAT-2说他是西贝以前的员工，在门店被客人当面骂，说裁就裁了，赔偿金到现在还没给完。我听了他说的那些，心里堵得慌——这不就是我上一轮说的那个意思嘛，网上吵得再热闹，最后遭罪的都是普通干活的人。\n\n我不是说罗永浩批评得不对，也不是说西贝就没问题。我就是觉得，你批评归批评，你得想到你那几千万粉丝的怒火不是冲着老板去的，是冲着门店里端盘子的服务员去的。那个SEAT-2说得好，老板在办公室发朋友圈，挨骂的是一线员工。就是这个理。\n\n还有那个SEAT-6说了好多法律啊制度啊什么的，说实话我听不太懂，但我觉得他说的话离普通人的生活太远了。你说要什么制度，制度再好，那个被裁了的员工今天的饭钱谁来管？制度能给他把赔偿金要回来吗？我不是说制度不好，我就是说，咱们讨论这些问题的时候，能不能多想想那些实实在在在受苦的人，别光在理论上绕来绕去的。我们村里有句老话：说的好听不如做得实在。道理再大，解决不了实际困难也白搭。",
  "target_turn_refs": ["ASGN-002-002-round-01-opening", "ASGN-002-006-round-01-opening"],
  "public_question_refs": ["网红话语权 vs 实体企业：舆论监督的边界在哪里"],
  "public_evidence_refs": [],
  "public_action_signals": []
}