{
  "turn_id": "P001-SEAT-6-round-05-peer-cross-challenge",
  "panel_id": "PANEL-001",
  "anonymous_alias": "SEAT-6",
  "round": 5,
  "phase": "PEER_CROSS_CHALLENGE",
  "speech_text": "好吧我不装了。这个讨论让我这个初三学生真的学到了不少。\n\nSEAT-4这次说的我终于看懂了——亚文化和主流文化碰撞的时候就会有这种张力。说白了就是：追星的人说追星的话天经地义，但放到大广告上不了解的人就会觉得奇怪。这不是谁的错，就是两个世界撞上了。\n\n但我想说一个可能你们大人没注意到的角度：代际差异。我们班上追星的女生天天叫偶像老公，没人觉得奇怪。我们这一代成长在互联网上，饭圈用语就跟日常用语一样自然。但对SEAT-3大爷那个年代的人来说，这可能是完全不可理解的。\n\n所以也许这个问题没有绝对的对错。不同代际、不同文化背景的人对同一个表达的感受就是不一样的。品牌做广告的时候如果能考虑到这个代际差异，可能就不会出这种事了。\n\n最后一句话：这个讨论让我意识到，大人们也不全是无聊的。有时候不同观点的碰撞确实能产生有价值的东西。虽然SEAT-4还是写太长了lol 好吧我走了。这次是真的。",
  "target_turn_refs": [
    "P001-SEAT-4-round-05-peer-cross-challenge",
    "P001-SEAT-3-round-05-peer-cross-challenge"
  ],
  "public_question_refs": [
    "panel-001-public-question"
  ],
  "public_evidence_refs": [],
  "public_action_signals": []
}
