{
  "turn_id": "ASGN-001-003-round-05-peer-cross-challenge",
  "panel_id": "PANEL-001",
  "anonymous_alias": "SEAT-3",
  "round": 5,
  "phase": "PEER_CROSS_CHALLENGE",
  "speech_text": "SEAT-1你担心标签化误伤好企业，我理解。但我想提一个这五轮讨论都没怎么触及的问题——定义之争的背后，其实是利益分配之争。\n\n我干了二十年厨房，太清楚了。中央厨房模式最大的好处是什么？降成本。集中采购、统一加工、减少人工、简化后厨——一个中央厨房可以替代十几个厨师。这些省下来的钱去哪了？企业拿了。消费者吃到的是降了品质的菜，付的却是原来的价。\n\nSEAT-1你想一想——你带一家人去西贝，一顿饭花多少钱？如果西贝用了中央厨房预加工降低了成本，它的价格降了吗？没有。你花的是'厨师现做'的钱，吃的是'中央厨房预加工'的菜。你觉得这个信息不对称影响的是认知还是钱包？\n\n所以消费者愤怒的深层原因不只是'被骗了'，而是'花了冤枉钱'。如果我花二百块吃一顿厨师手艺做的菜，那是物有所值；但如果这顿菜是料包加热的，成本可能只有五十块，那我多花的一百五十块是什么？是信息不对称的溢价。\n\n定义之争争到最后，核心不是法规定义对不对，而是消费者有没有被公平对待。你用中央厨房可以，但你得告诉消费者，让消费者决定这个价值不值。这才叫公平。\n\nSEAT-2说得对——标签不会误伤好企业。如果一个企业品质过硬、价格合理，消费者看了标签还会买单。但如果一个企业靠信息不对称赚差价，那被标签'伤害'也是应得的。",
  "target_turn_refs": [
    "ASGN-001-001-round-05-peer-cross-challenge",
    "ASGN-001-002-round-05-peer-cross-challenge"
  ],
  "public_question_refs": [
    "预制菜定义之争：法规标准与消费者认知的冲突"
  ],
  "public_evidence_refs": [],
  "public_action_signals": []
}
