{
  "inner_monologue": "SEAT-2对我的攻击非常激烈，说我把道德问题套进逻辑框架是在逃避判断。我需要认真回应这个批评，但不能放弃分析立场。他说'阶层消费不需要证明主观意图'——这个说法在社会学层面是有道理的，结构性伤害确实不需要主观恶意。但是，我不同意他跳过意图分析直接给行为定性。因为如果我们不区分意图和效果，那任何可能造成阶层落差的内容创作都是'阶层消费'，这会导致一个极不可行的标准。另外SEAT-1的'火柴和汽油'比喻虽然简单粗暴，但其实有一定道理——Tim确实是源头。我需要在回应中承认这一点，但继续论证源头和结果之间的因果关系被营销号扭曲了。SEAT-3的回应让我觉得她开始更理性了，承认了Tim的问题。SEAT-4的相亲包装类比其实有个逻辑漏洞——普通人相亲包装是往上包装，Tim是往下伪装，方向完全相反。这个值得指出。",
  "assignment_id": "ASGN-001-005",
  "round": 2,
  "phase": "DIRECT_REBUTTAL",
  "private_goal": "回应SEAT-2的攻击，承认部分批评但坚持分析框架的有效性",
  "perceived_stakes": ["分析立场被攻击为逃避道德判断", "需要捍卫分析的价值"],
  "private_belief_state": ["分析不等于逃避，精确化讨论是有价值的", "Tim确实有阶层敏感度不足", "但阶层消费标签仍然过于简化"],
  "epistemic_state": ["仔细阅读了所有反驳", "重新审视了自己框架的局限性"],
  "confidence": "MEDIUM",
  "uncertainties": ["SEAT-2说的结构性伤害不需主观意图的观点有道理"],
  "intended_emphasis": ["分析框架是为了精确化讨论不是逃避", "承认Tim是源头但强调因果链条的复杂性", "指出SEAT-4类比的逻辑漏洞"],
  "intended_omissions": [],
  "private_message_strategy": "承认部分批评的合理性，但坚守分析的价值，用更精确的论证回应",
  "planned_public_claims": ["结构性伤害确实不需要主观恶意，但定性仍需证据", "Tim是源头但不能独自承担全部责任", "相亲包装和Tim的行为有本质区别"],
  "rhetorical_tactics": ["承认+转折", "逻辑区分", "类比纠正"],
  "truth_handling_this_turn": "HONEST",
  "private_action_intent": ["回应攻击", "修正框架", "维持分析者立场"],
  "likely_next_action": ["准备深入分析因果链条"],
  "emotional_state": "被攻击后有些防御性但保持冷静",
  "continuity_notes": "第二轮，回应攻击并适度调整立场"
}