{
  "turn_id": "ASGN-001-001-round-03-peer-cross",
  "panel_id": "PANEL-001",
  "anonymous_alias": "SEAT-1",
  "round": 3,
  "phase": "PEER_CROSS_CHALLENGE",
  "speech_text": "我要直接挑战几个说法。\n\nSEAT-4大姐，你上一轮说'相亲本来就有包装，大家都包装'，把你儿子说自己是'做管理工作的'和Tim写'国内初中学历'等同起来。大姐我尊重你，但这两个不一样。你儿子说'做管理'是因为觉得自己工作不够体面，想往上说一点，这是自卑。Tim说'国内初中学历'是因为他知道自己的真实学历太厉害了，他要故意往下说，制造反差。一个是想让自己看起来好一点，一个是故意让自己看起来差一点。方向完全相反，动机完全不同。\n\n你儿子去相亲，不管他说不说实话，他去是因为真的想找对象。Tim去相亲角是为了拍视频。你儿子的真诚和Tim的表演，能一样吗？你想想，如果有人到你工作的超市来，假装自己是顾客，把你认真收银的样子拍下来发网上，配上'看看这个收银员多认真多土'的标题——你觉得这跟你儿子相亲包装自己是一回事吗？\n\nSEAT-3你说Tim在视频里没有嘲笑行为，态度平和。我说你只看到了表面。什么叫嘲笑？只有嘴巴上说笑话才算嘲笑吗？一个亿万富翁假装成初中学历的穷小子去相亲角被嫌弃——当真相曝光的时候，那些大妈的嫌弃、她们说的'学历太低了'，都变成了笑料。大妈们认真地评判了一份假简历，她们的认真变成了全网的笑点。这种嘲笑不需要Tim说一个字的笑话，整个行为本身就是对她们真诚的嘲弄。不是嘴巴上嘲笑才叫嘲笑，拿别人的认真当乐子也是嘲笑。",
  "target_turn_refs": [
    "ASGN-001-004-round-02-direct-rebuttal",
    "ASGN-001-003-round-02-direct-rebuttal"
  ],
  "public_question_refs": [
    "富人伪装底层去相亲角，是创意内容还是阶层消费？"
  ],
  "public_evidence_refs": [
    "C001",
    "C011"
  ],
  "public_action_signals": []
}
