{
  "inner_monologue": "讨论到了第四轮，SEAT-2提出了一个非常有力的论点：制度太慢了等不起。这个现实问题不能回避。我需要给出更具体的实施路径和时间表来回应这个合理的质疑。SEAT-4提出的'制度与舆论互补'的框架实际上是我可以接受的折中——舆论作为补充存在但在制度框架内运作。SEAT-5提出的商业生态维度很有深度，他说正义在流量经济中是有价格的——这个洞察我之前没深入思考过。他说的对，流量逻辑扭曲了信息传播的方向和力度，这确实是一个更深层的问题。我可以在此基础上提出更完整的方案：制度化的框架加舆论的补充，同时通过算法透明度和平台责任来约束流量逻辑的扭曲。这轮我想回应SEAT-2的时效性质疑——给出更具体的推进建议，同时整合大家的共识。",
  "assignment_id": "ASGN-002-006",
  "round": 4,
  "phase": "RESPONSIVE_REBUTTAL",
  "private_goal": "回应SEAT-2的时效性质疑，整合讨论中的共识，提出更完整的制度加舆论框架",
  "perceived_stakes": ["自己分析框架的完整性", "制度方案的可行性"],
  "private_belief_state": ["制度与舆论互补是最合理的框架", "SEAT-5的商业生态分析是重要补充", "需要回应时效性质疑"],
  "epistemic_state": ["整合了多方观点", "准备提出综合方案"],
  "confidence": "HIGH",
  "uncertainties": ["不确定综合方案能否回应所有质疑"],
  "intended_emphasis": ["回应时效性质疑", "整合共识", "提出综合框架"],
  "intended_omissions": ["不深入讨论SEAT-5可能的动机问题"],
  "private_message_strategy": "整合各方观点形成综合方案，回应实际质疑",
  "planned_public_claims": ["制度与舆论互补是最合理的框架", "具体推进可以分阶段", "SEAT-5的商业生态分析是重要补充"],
  "rhetorical_tactics": ["整合各方论点显得客观", "给出具体回应显得务实", "提出综合方案显得有建设性"],
  "truth_handling_this_turn": "HONEST",
  "private_action_intent": ["形成综合方案", "推动讨论走向建设性结论"],
  "likely_next_action": ["最后两轮做总结"],
  "emotional_state": "理性满意，觉得讨论有了实质性进展",
  "continuity_notes": "第四轮，整合各方观点提出制度加舆论的综合框架，回应了时效性质疑",
  "raw_chain_of_thought_saved": false
}