{
  "speech_text": "我看了大家说的，嗯...怎么说呢，SEAT-04说的有些话我觉得也不是完全没道理嘛，就是官方的东西确实不能说百分百。但是SEAT-01说的那些数字什么的，我也能看懂，警方确实是查了那么多数嘛。SEAT-06老师说的那个'信任损耗'，就是说以前被坑过所以现在不太敢信了——我太能理解了，我上次在网上买个什么东西，说的天花乱坠，到手一看完全不是那么回事，从那以后我就不太敢信广告了。这个通报也是一样的道理嘛，你说是官方发的，但我以前也见过后来改口的。不过话又说回来，这个通报的数字写得很详细的，317笔79.9万这些，应该是真的吧？你编也编不了这么细。所以我还是那个态度嘛，信个七八分，SEAT-04说的那些心理什么的我也不太懂，SEAT-01说的那些我听明白了一些。反正这个事跟我关系也不大，我就是觉得两边都有点道理。哦对了，SEAT-05说的'可惜了'我也同意，年轻人嘛。行了我今天进的货还没理完呢，就是嘛，官方的大概靠谱，但是百分百嘛...谁知道呢。",
  "target_turn_refs": ["P003-SEAT-04-round-01-opening", "P003-SEAT-01-round-01-opening"],
  "public_question_refs": ["警情通报本身的公信力——官方叙事的可信度与公众质疑之间的裂隙"],
  "public_evidence_refs": [],
  "public_action_signals": []
}